benchmarks/__init__.py
benchmarks/datasets.py
benchmarks/ops.py
benchmarks/utils.py
pangeobench-0.1.data/scripts/pangeobench
pangeobench-0.1.dist-info/LICENSE
pangeobench-0.1.dist-info/METADATA
pangeobench-0.1.dist-info/WHEEL
pangeobench-0.1.dist-info/top_level.txt
pangeobench-0.1.dist-info/RECORD
