Metadata-Version: 2.1
Name: pangeobench
Version: 0.1
Summary: Pangeo zarr benchmarking package
Home-page: https://github.com/pangeo-data/benchmarking
Author: Haiying Xu
Author-email: haiyingx@ucar.com
License: UNKNOWN
Platform: UNKNOWN
Classifier: Programming Language :: Python :: 3
Classifier: License :: OSI Approved :: MIT License
Classifier: Operating System :: OS Independent
